fastbench/__init__.py
fastbench-0.1.5.dist-info/LICENSE
fastbench-0.1.5.dist-info/METADATA
fastbench-0.1.5.dist-info/WHEEL
fastbench-0.1.5.dist-info/RECORD
