Metadata-Version: 2.1
Name: fastbench
Version: 0.1.5
Summary: A pure-python based benchmarking package for Python 🤪
Home-page: https://github.com/itsmeadarsh2008/fastbench
License: MIT
Keywords: bench,fastbench,benchmark,pure,python,simple,performance,package,code,execution,time,cpu,memory,usage,lightweight,api,measure,function,track,monitor,test,efficiency,speed,algorithm,script,development,debugging,optimized,library,analyze,profile,scalable,reliable,tool,optimizations,profiling,debug,evaluate,performance testing,profiler,codebase,analytical,scalability,efficiency,analyzing,optimization,code optimization,proficiency,analytic,performance analysis
Author: Adarsh Gourab Mahalik
Author-email: gourabmahalikadarsh@gmail.com
Requires-Python: >=3.8,<4.0
Classifier: License :: OSI Approved :: MIT License
Classifier: Programming Language :: Python :: 3
Classifier: Programming Language :: Python :: 3.8
Classifier: Programming Language :: Python :: 3.9
Classifier: Programming Language :: Python :: 3.10
Classifier: Programming Language :: Python :: 3.11
Classifier: Programming Language :: Python :: 3.12
Requires-Dist: psutil (>=5.9.8,<6.0.0)
Project-URL: Bug Tracker, https://github.com/itsmeadarsh2008/fastbench/issues
Project-URL: Repository, https://github.com/itsmeadarsh2008/fastbench.git
